neon_phal_plugin_core_updater/__init__.py
neon_phal_plugin_core_updater-1.3.0.dist-info/LICENSE.md
neon_phal_plugin_core_updater-1.3.0.dist-info/METADATA
neon_phal_plugin_core_updater-1.3.0.dist-info/WHEEL
neon_phal_plugin_core_updater-1.3.0.dist-info/entry_points.txt
neon_phal_plugin_core_updater-1.3.0.dist-info/top_level.txt
neon_phal_plugin_core_updater-1.3.0.dist-info/RECORD
