Metadata-Version: 2.1
Name: neon-phal-plugin-core-updater
Version: 1.3.0
Summary: Core Module Update Interface
Home-page: https://github.com/NeonGeckoCom/neon-phal-plugin-core-updater
Author: Neongecko
Author-email: developers@neon.ai
License: BSD-3
License-File: LICENSE.md
Requires-Dist: requests
Requires-Dist: neon-utils ~=1.1
Requires-Dist: ovos-plugin-manager ~=0.0.20
Requires-Dist: ovos-bus-client ~=0.0.3
Requires-Dist: ovos-utils ~=0.0.30
